aradf/__init__.py
aradf/convertor.py
aradf-0.0.2.dist-info/LICENSE
aradf-0.0.2.dist-info/METADATA
aradf-0.0.2.dist-info/WHEEL
aradf-0.0.2.dist-info/top_level.txt
aradf-0.0.2.dist-info/RECORD
