Metadata-Version: 2.1
Name: aradf
Version: 0.0.2
Summary: For converting pdf documents to txt files
Home-page: https://github.com/Mutlaq0/aradf
Author: Mutlaq Hijazi
Author-email: Mutlaq.086@gmail.com
License: UNKNOWN
Platform: UNKNOWN
Classifier: Programming Language :: Python :: 3
Classifier: License :: OSI Approved :: MIT License
Classifier: Operating System :: OS Independent
Requires-Python: >=3.7
License-File: LICENSE
Requires-Dist: opencv-python
Requires-Dist: pytesseract
Requires-Dist: numpy
Requires-Dist: typing
Requires-Dist: PyMuPDF
Requires-Dist: Pillow
